README.txt
setup.py
src/affinitic/__init__.py
src/affinitic.recipe.fakezope2eggs.egg-info/PKG-INFO
src/affinitic.recipe.fakezope2eggs.egg-info/SOURCES.txt
src/affinitic.recipe.fakezope2eggs.egg-info/dependency_links.txt
src/affinitic.recipe.fakezope2eggs.egg-info/entry_points.txt
src/affinitic.recipe.fakezope2eggs.egg-info/namespace_packages.txt
src/affinitic.recipe.fakezope2eggs.egg-info/not-zip-safe
src/affinitic.recipe.fakezope2eggs.egg-info/requires.txt
src/affinitic.recipe.fakezope2eggs.egg-info/top_level.txt
src/affinitic/recipe/__init__.py
src/affinitic/recipe/fakezope2eggs/__init__.py